prerender_python_starlette/__init__.py
prerender_python_starlette/middleware.py
prerender_python_starlette-1.0.1.dist-info/LICENSE
prerender_python_starlette-1.0.1.dist-info/WHEEL
prerender_python_starlette-1.0.1.dist-info/METADATA
prerender_python_starlette-1.0.1.dist-info/RECORD
