Metadata-Version: 2.1
Name: prerender-python-starlette
Version: 1.0.1
Summary: Starlette middleware for Prerender.
Home-page: https://github.com/BeeMyDesk/prerender-python-starlette
License: UNKNOWN
Author: François Voron
Author-email: fvoron@gmail.com
Requires-Python: >=3.7
Classifier: Programming Language :: Python :: 3.7
Classifier: Programming Language :: Python :: 3.8
Classifier: Programming Language :: Python :: 3 :: Only
Requires-Dist: httpx >=0.11,<0.13
Project-URL: Documentation, https://BeeMyDesk.github.io/prerender-python-starlette/
